[[{"__type__":"cc.SceneAsset","_name":"GameLoading","scene":{"__id__":1},"asyncLoadAssets":null},{"__type__":"cc.Scene","_name":"New Node","_children":[{"__id__":2}],"_anchorPoint":{"__type__":"cc.Vec2"},"autoReleaseAssets":false},{"__type__":"cc.Node","_name":"Canvas","_parent":{"__id__":1},"_children":[{"__id__":3},{"__id__":4},{"__id__":8}],"_components":[{"__type__":"cc.Canvas","node":{"__id__":2},"_designResolution":{"__type__":"cc.Size","width":750,"height":1334}},{"__type__":"23512IMpdJAMpUoYedJc7MS","node":{"__id__":2},"progressBar":{"__id__":7}}],"_id":"49Bk3Z87RBqpQSfp04vT+k","_contentSize":{"__type__":"cc.Size","width":750,"height":1334},"_position":{"__type__":"cc.Vec2","x":375,"y":667}},{"__type__":"cc.Node","_name":"Background","_parent":{"__id__":2},"_components":[{"__type__":"cc.Sprite","node":{"__id__":3},"_spriteFrame":{"__uuid__":"72R5pB9E1LK5l27D0OByR1"},"_sizeMode":0}],"_color":{"__type__":"cc.Color","r":189,"g":235,"b":106},"_contentSize":{"__type__":"cc.Size","width":800,"height":1340}},{"__type__":"cc.Node","_name":"LoadBar","_parent":{"__id__":2},"_children":[{"__id__":5}],"_active":false,"_components":[{"__id__":7},{"__type__":"cc.Sprite","node":{"__id__":4},"_spriteFrame":{"__uuid__":"81VKeyv/xLwZ5rF437YFjI"},"_type":1,"_sizeMode":0}],"_color":{"__type__":"cc.Color","r":211,"g":20,"b":20},"_contentSize":{"__type__":"cc.Size","width":700,"height":61}},{"__type__":"cc.Node","_name":"bg","_parent":{"__id__":4},"_components":[{"__id__":6}],"_contentSize":{"__type__":"cc.Size","width":700,"height":51}},{"__type__":"cc.Sprite","node":{"__id__":5},"_spriteFrame":{"__uuid__":"81VKeyv/xLwZ5rF437YFjI"},"_type":1,"_sizeMode":0},{"__type__":"cc.ProgressBar","node":{"__id__":4},"_N$totalLength":700,"_N$barSprite":{"__id__":6}},{"__type__":"cc.Node","_name":"Label","_parent":{"__id__":2},"_active":false,"_components":[{"__type__":"cc.Label","node":{"__id__":8},"_useOriginalSize":false,"_N$string":"Game loading...","_N$horizontalAlign":1,"_N$verticalAlign":1}],"_color":{"__type__":"cc.Color","r":54,"g":28,"b":28},"_contentSize":{"__type__":"cc.Size","width":282,"height":40},"_position":{"__type__":"cc.Vec2","y":100}}],{"__type__":"cc.SpriteFrame","content":{"name":"logothi","texture":"060q79vtRDVaosYKQumwDM","rect":[0,0,751,1334],"offset":[-6.5,0],"originalSize":[764,1334]}},{"__type__":"cc.SpriteFrame","content":{"name":"bg","texture":"25eMYLjydOCIDnKyfSLzK4","rect":[0,0,10,10],"offset":[0,0],"originalSize":[10,10]}}]